fiducialreg/__init__.py
fiducialreg/fiducialreg.py
fiducialreg/imref.py
fiducialreg/imwarp.py
llspy/__init__.py
llspy/__main__.py
llspy/_version.py
llspy/arrayfun.py
llspy/camcalib.py
llspy/camera.py
llspy/compress.py
llspy/config.py
llspy/cudabinwrapper.py
llspy/exceptions.py
llspy/libcudawrapper.py
llspy/libinstall.py
llspy/llsdir.py
llspy/otf.py
llspy/parse.py
llspy/register_old.py
llspy/samples.py
llspy/schema.py
llspy/settingstxt.py
llspy/util.py
llspy/xzpsf.py
llspy/bin/__init__.py
llspy/bin/llspy_cli.py
llspy/bin/llspy_gui.py
llspy/gui/__init__.py
llspy/gui/before_after.png
llspy/gui/camcalibgui.py
llspy/gui/camcordialog.py
llspy/gui/camcordialog.ui
llspy/gui/exceptions.py
llspy/gui/guiDefaults.ini
llspy/gui/helpers.py
llspy/gui/img_dialog.py
llspy/gui/img_window.py
llspy/gui/img_window.ui
llspy/gui/logo_dark.png
llspy/gui/logo_light.png
llspy/gui/main_gui.py
llspy/gui/main_gui.ui
llspy/gui/mainwindow.py
llspy/gui/qtlogger.py
llspy/gui/styles.py
llspy/gui/watcher.py
llspy/gui/workers.py
llspy-0.5.1.dist-info/LICENSE
llspy-0.5.1.dist-info/METADATA
llspy-0.5.1.dist-info/WHEEL
llspy-0.5.1.dist-info/entry_points.txt
llspy-0.5.1.dist-info/top_level.txt
llspy-0.5.1.dist-info/RECORD
