Metadata-Version: 2.1
Name: llspy
Version: 0.5.1
Summary: Lattice Light Sheet Processing Tools.
Author-email: Talley Lambert <talley.lambert@example.com>
License: BSD-3-Clause
Project-URL: homepage, https://github.com/tlambert03/LLSpy
Project-URL: repository, https://github.com/tlambert03/LLSpy
Classifier: Development Status :: 3 - Alpha
Classifier: Intended Audience :: Science/Research
Classifier: License :: OSI Approved :: BSD License
Classifier: Natural Language :: English
Classifier: Operating System :: Microsoft :: Windows
Classifier: Operating System :: POSIX :: Linux
Classifier: Programming Language :: Python
Classifier: Programming Language :: Python :: 3 :: Only
Classifier: Programming Language :: Python :: 3.7
Classifier: Programming Language :: Python :: 3.8
Classifier: Programming Language :: Python :: 3.9
Classifier: Programming Language :: Python :: 3.10
Classifier: Programming Language :: Python :: 3.11
Classifier: Topic :: Scientific/Engineering :: Visualization
Requires-Python: >=3.7
License-File: LICENSE
Requires-Dist: click ~=8.1
Requires-Dist: llspy-slm >=0.2.1
Requires-Dist: matplotlib
Requires-Dist: numpy
Requires-Dist: parse ~=1.20
Requires-Dist: qtpy >=2.4
Requires-Dist: scipy <=1.12
Requires-Dist: sentry-sdk ~=1.38
Requires-Dist: tifffile
Requires-Dist: voluptuous ~=0.14
Requires-Dist: watchdog ~=3.0
Requires-Dist: numba ; python_version < "3.13"
Requires-Dist: importlib-metadata ; python_version < "3.8"
Provides-Extra: dev
Requires-Dist: ipython ; extra == 'dev'
Requires-Dist: mypy ; extra == 'dev'
Requires-Dist: pdbpp ; extra == 'dev'
Requires-Dist: pre-commit ; extra == 'dev'
Requires-Dist: rich ; extra == 'dev'
Requires-Dist: ruff ; extra == 'dev'
Provides-Extra: napari
Requires-Dist: napari ; extra == 'napari'
Provides-Extra: pyqt5
Requires-Dist: PyQt5 ; extra == 'pyqt5'
Provides-Extra: pyside2
Requires-Dist: PySide2 ; extra == 'pyside2'
Provides-Extra: spimagine
Requires-Dist: spimagine ; extra == 'spimagine'
Provides-Extra: test
Requires-Dist: pytest ; extra == 'test'
Requires-Dist: pytest-cov ; extra == 'test'
Requires-Dist: pytest-qt ; extra == 'test'
